{"nodes": [{"id": "lib_services_version_service_dart", "label": "version_service.dart", "file_type": "code", "source_file": "lib\\services\\version_service.dart", "source_location": null}, {"id": "lib_services_version_service_dart_versioncheckresult", "label": "VersionCheckResult", "file_type": "code", "source_file": "lib\\services\\version_service.dart", "source_location": null}, {"id": "lib_services_version_service_dart_appversion", "label": "AppVersion", "file_type": "code", "source_file": "lib\\services\\version_service.dart", "source_location": null}, {"id": "lib_services_version_service_dart_versionservice", "label": "VersionService", "file_type": "code", "source_file": "lib\\services\\version_service.dart", "source_location": null}, {"id": "lib_services_version_service_dart_parsejson", "label": "_parseJson", "file_type": "code", "source_file": "lib\\services\\version_service.dart", "source_location": null}, {"id": "lib_services_version_service_dart_exception", "label": "Exception", "file_type": "code", "source_file": "lib\\services\\version_service.dart", "source_location": null}, {"id": "lib_services_version_service_dart_isversionhigher", "label": "_isVersionHigher", "file_type": "code", "source_file": "lib\\services\\version_service.dart", "source_location": null}, {"id": "lib_services_version_service_dart_cleanver", "label": "_cleanVer", "file_type": "code", "source_file": "lib\\services\\version_service.dart", "source_location": null}, {"id": "dart_convert", "label": "dart:convert", "file_type": "code", "source_file": "lib\\services\\version_service.dart", "source_location": null}, {"id": "package_http_http_dart", "label": "package:http/http.dart", "file_type": "code", "source_file": "lib\\services\\version_service.dart", "source_location": null}, {"id": "dart_io", "label": "dart:io", "file_type": "code", "source_file": "lib\\services\\version_service.dart", "source_location": null}, {"id": "package_shared_preferences_shared_preferences_dart", "label": "package:shared_preferences/shared_preferences.dart", "file_type": "code", "source_file": "lib\\services\\version_service.dart", "source_location": null}, {"id": "package_package_info_plus_package_info_plus_dart", "label": "package:package_info_plus/package_info_plus.dart", "file_type": "code", "source_file": "lib\\services\\version_service.dart", "source_location": null}], "edges": [{"source": "lib_services_version_service_dart", "target": "lib_services_version_service_dart_versioncheckresult", "relation": "defines", "confidence": "EXTRACTED", "confidence_score": 1.0, "source_file": "lib\\services\\version_service.dart", "source_location": null, "weight": 1.0}, {"source": "lib_services_version_service_dart", "target": "lib_services_version_service_dart_appversion", "relation": "defines", "confidence": "EXTRACTED", "confidence_score": 1.0, "source_file": "lib\\services\\version_service.dart", "source_location": null, "weight": 1.0}, {"source": "lib_services_version_service_dart", "target": "lib_services_version_service_dart_versionservice", "relation": "defines", "confidence": "EXTRACTED", "confidence_score": 1.0, "source_file": "lib\\services\\version_service.dart", "source_location": null, "weight": 1.0}, {"source": "lib_services_version_service_dart", "target": "lib_services_version_service_dart_parsejson", "relation": "defines", "confidence": "EXTRACTED", "confidence_score": 1.0, "source_file": "lib\\services\\version_service.dart", "source_location": null, "weight": 1.0}, {"source": "lib_services_version_service_dart", "target": "lib_services_version_service_dart_exception", "relation": "defines", "confidence": "EXTRACTED", "confidence_score": 1.0, "source_file": "lib\\services\\version_service.dart", "source_location": null, "weight": 1.0}, {"source": "lib_services_version_service_dart", "target": "lib_services_version_service_dart_isversionhigher", "relation": "defines", "confidence": "EXTRACTED", "confidence_score": 1.0, "source_file": "lib\\services\\version_service.dart", "source_location": null, "weight": 1.0}, {"source": "lib_services_version_service_dart", "target": "lib_services_version_service_dart_cleanver", "relation": "defines", "confidence": "EXTRACTED", "confidence_score": 1.0, "source_file": "lib\\services\\version_service.dart", "source_location": null, "weight": 1.0}, {"source": "lib_services_version_service_dart", "target": "dart_convert", "relation": "imports", "confidence": "EXTRACTED", "confidence_score": 1.0, "source_file": "lib\\services\\version_service.dart", "source_location": null, "weight": 1.0}, {"source": "lib_services_version_service_dart", "target": "package_http_http_dart", "relation": "imports", "confidence": "EXTRACTED", "confidence_score": 1.0, "source_file": "lib\\services\\version_service.dart", "source_location": null, "weight": 1.0}, {"source": "lib_services_version_service_dart", "target": "dart_io", "relation": "imports", "confidence": "EXTRACTED", "confidence_score": 1.0, "source_file": "lib\\services\\version_service.dart", "source_location": null, "weight": 1.0}, {"source": "lib_services_version_service_dart", "target": "package_shared_preferences_shared_preferences_dart", "relation": "imports", "confidence": "EXTRACTED", "confidence_score": 1.0, "source_file": "lib\\services\\version_service.dart", "source_location": null, "weight": 1.0}, {"source": "lib_services_version_service_dart", "target": "package_package_info_plus_package_info_plus_dart", "relation": "imports", "confidence": "EXTRACTED", "confidence_score": 1.0, "source_file": "lib\\services\\version_service.dart", "source_location": null, "weight": 1.0}]}